low/__init__.py
low/base.py
low-0.1.0.dev0.dist-info/WHEEL
low-0.1.0.dev0.dist-info/METADATA
low-0.1.0.dev0.dist-info/RECORD
